server/__init__.py
server/alphaspace.py
server/app.py
server/cli.py
server/handlers.py
server/readers.py
server/run_app.py
server/alphaspace2/Cluster.py
server/alphaspace2/Community.py
server/alphaspace2/Configs.py
server/alphaspace2/Features.py
server/alphaspace2/Snapshot.py
server/alphaspace2/Trajectory.py
server/alphaspace2/View.py
server/alphaspace2/VinaScoring.py
server/alphaspace2/__init__.py
server/alphaspace2/functions.py
server/alphaspace2/data/AS_Chimera_alpha.py
server/alphaspace2/data/AS_Chimera_beta.py
server/alphaspace2/data/amber_types_fine.dat
server/alphaspace2/data/autodock_atom_type_info.dat
server/alphaspace2/data/colors_chimera.txt
server/alphaspace2/data/colors_table.txt
server/alphaspace2/data/hp_types_dict.dat
server/alphaspace2/data/typing_from_pdb.dat
server/alphaspace2/data/vina_params.dat
trajolecule-1.7.0rc1.dist-info/METADATA
trajolecule-1.7.0rc1.dist-info/WHEEL
trajolecule-1.7.0rc1.dist-info/entry_points.txt
trajolecule-1.7.0rc1.dist-info/RECORD
