Metadata-Version: 2.4
Name: trajolecule
Version: 1.7.0rc1
Summary: MD trajectory viewer
Project-URL: Homepage, https://github.com/boscoh/trejolecule
Author-email: Bosco Ho <apposite@gmail.com>
Requires-Python: >=3.9
Requires-Dist: addict
Requires-Dist: easytrajh5>=0.2.17
Requires-Dist: fastapi
Requires-Dist: mdtraj>=1.9.10
Requires-Dist: numpy<2.0
Requires-Dist: path
Requires-Dist: psutil
Requires-Dist: pydash
Requires-Dist: python-multipart
Requires-Dist: rdkit
Requires-Dist: rich
Requires-Dist: starlette
Requires-Dist: uvicorn
